getBISy/__init__.py
getBISy/data.py
getBISy/enums.py
getBISy/fetcher.py
getbisy-0.0.12.dist-info/METADATA
getbisy-0.0.12.dist-info/WHEEL
getbisy-0.0.12.dist-info/top_level.txt
getbisy-0.0.12.dist-info/RECORD
