Metadata-Version: 2.4
Name: getBISy
Version: 0.0.12
Summary: package description
Author-email: Matthew Potts <matthew-potts@live.com>
Requires-Python: >=3.11
